mwclient/__init__.py
mwclient/client.py
mwclient/errors.py
mwclient/image.py
mwclient/listing.py
mwclient/page.py
mwclient/sleep.py
mwclient/util.py
mwclient-0.10.1.dist-info/LICENSE.md
mwclient-0.10.1.dist-info/METADATA
mwclient-0.10.1.dist-info/WHEEL
mwclient-0.10.1.dist-info/top_level.txt
mwclient-0.10.1.dist-info/zip-safe
mwclient-0.10.1.dist-info/RECORD
