Metadata-Version: 2.1
Name: mwclient
Version: 0.10.1
Summary: MediaWiki API client
Home-page: https://github.com/btongminh/mwclient
Author: Bryan Tong Minh
Author-email: bryan.tongminh@gmail.com
License: MIT
Keywords: mediawiki wikipedia
Platform: UNKNOWN
Classifier: Programming Language :: Python
Classifier: Programming Language :: Python :: 2.7
Classifier: Programming Language :: Python :: 3.5
Classifier: Programming Language :: Python :: 3.6
Classifier: Programming Language :: Python :: 3.7
Classifier: Programming Language :: Python :: 3.8
